{
    "namedEntities": {
        "persons": {
            "p_1": "R. D. OLiver",
            "p_2": "A. U. Willis"
        },
        "locations": {
            "l_1": "Balboa",
            "l_2": "South Atlantic",
            "l_3": "Cape"
        },
        "events": {
            "e_1": "Sinking of the German Supply Ship PYTHON",
            "e_2": "Action of H.M.S. DEVONSHIRE on 23rd November"
        },
        "organisations": {
            "o_1": "Admiralty",
            "o_2": "H.M.S. DEVONSHIRE",
            "o_3": "DORSETSHIRE",
            "o_4": "Corvettes ASTER",
            "o_5": "Corvettes MARGUERITE"
        }
    },
    "keywords": [
        "sinking",
        "raider",
        "submarine threat",
        "survivors",
        "Admiralty"
    ],
    "themes": [
        "Military Operations",
        "Naval Warfare",
        "Survival and Rescue"
    ],
    "topicModel": {
        "Military Operations": [
            "e_1",
            "e_2"
        ],
        "Naval Warfare": [
            "e_1",
            "e_2"
        ],
        "Survival and Rescue": [
            "e_1"
        ]
    },
    "eventConnections": [
        {
            "event": "e_1",
            "date": "29th December, 1941",
            "locations": [
                "l_2",
                "l_3"
            ],
            "persons": [
                "p_2"
            ],
            "organisations": [
                "o_1",
                "o_2"
            ],
            "connectedEvents": [
                "e_2"
            ],
            "eventSummary": "On 29th December, 1941, Vice-Admiral A. U. Willis submits a report on the sinking of the German supply ship PYTHON, noting its significant impact on submarine threats in the Cape area."
        },
        {
            "event": "e_2",
            "date": "23rd November",
            "locations": [
                "l_3"
            ],
            "persons": [
                "p_1"
            ],
            "organisations": [
                "o_1",
                "o_2",
                "o_4",
                "o_5"
            ],
            "connectedEvents": [
                "e_1"
            ],
            "eventSummary": "On 23rd November, H.M.S. DEVONSHIRE sinks an enemy raider, contributing to a strategic reduction of the submarine threat in the region."
        }
    ]
}