{
    "namedEntities": {
        "persons": {
            "p_1": "Generalissimo",
            "p_2": "Mr. Stewart"
        },
        "locations": {
            "l_1": "Rangoon",
            "l_2": "Kyaikto",
            "l_3": "Lashio",
            "l_4": "Chungking",
            "l_5": "Mokpalin",
            "l_6": "River Sittang"
        },
        "events": {
            "e_1": "Withdrawal of 17 Indian Division",
            "e_2": "Visit to Lashio"
        },
        "organisations": {
            "o_1": "Burma Railways",
            "o_2": "R.A.F."
        }
    },
    "keywords": [
        "withdrawal",
        "reinforcements",
        "defence",
        "bombing",
        "communications",
        "evacuation"
    ],
    "themes": [
        "Military Operations",
        "Coordination",
        "Evacuation",
        "Communication Issues"
    ],
    "topicModel": {
        "Military Operations": [
            "e_1",
            "e_2"
        ],
        "Coordination": [
            "e_1"
        ],
        "Evacuation": [
            "e_1"
        ],
        "Communication Issues": [
            "e_1",
            "e_2"
        ]
    },
    "eventConnections": [
        {
            "event": "e_1",
            "date": "22nd February 1690",
            "locations": [
                "l_1",
                "l_2",
                "l_6"
            ],
            "persons": [
                "p_1"
            ],
            "organisations": [
                "o_1",
                "o_2"
            ],
            "connectedEvents": [
                "e_2"
            ],
            "eventSummary": "The 17 Indian Division successfully begins its withdrawal from the River Sittang after heavy fighting. The operation involves coordination between different brigades to retreat safely, despite challenges like bombing attacks and difficult communication."
        },
        {
            "event": "e_2",
            "date": "21st February 1690",
            "locations": [
                "l_3",
                "l_4"
            ],
            "persons": [
                "p_1"
            ],
            "organisations": [
                "o_1"
            ],
            "connectedEvents": [
                "e_1"
            ],
            "eventSummary": "The Generalissimo's visit to Lashio is intended to facilitate the arrival of Chinese troops in Burma. However, he decides not to land, leading to missed opportunities in coordinating reinforcements."
        }
    ]
}