{
    "namedEntities": {
        "persons": {
            "p_1": "Professor A. V. Hill"
        },
        "locations": {
            "l_1": "Petersham",
            "l_2": "London",
            "l_3": "Solent",
            "l_4": "Humber",
            "l_5": "Tyne-Tees",
            "l_6": "Forth",
            "l_7": "Clyde"
        },
        "events": {
            "e_1": "Battle against the Luftwaffe"
        },
        "organisations": {
            "o_1": "Army Operational Research Group",
            "o_2": "R.A.F.",
            "o_3": "Anti-Aircraft Command"
        }
    },
    "keywords": [
        "Anti-Aircraft",
        "training",
        "Militia",
        "Territorial Army",
        "scientists",
        "radio-location",
        "radar",
        "aircraft factories",
        "Gun Defended Areas",
        "defences"
    ],
    "themes": [
        "Military Operations",
        "Training and Development",
        "Technological Advancements"
    ],
    "topicModel": {
        "Military Operations": [
            "e_1"
        ],
        "Training and Development": [],
        "Technological Advancements": []
    },
    "eventConnections": [
        {
            "event": "e_1",
            "date": "1941",
            "locations": [
                "l_2",
                "l_3",
                "l_4",
                "l_5",
                "l_6",
                "l_7"
            ],
            "persons": [
                "p_1"
            ],
            "organisations": [
                "o_1",
                "o_2",
                "o_3"
            ],
            "connectedEvents": [],
            "eventSummary": "The battle against the Luftwaffe is an ongoing military operation focused on defending against enemy air attacks targeting key objectives."
        }
    ]
}