{
    "namedEntities": {
        "persons": {
            "p_1": "General Chennault",
            "p_2": "Group Captain Seton Broughall",
            "p_3": "General Alexander"
        },
        "locations": {
            "l_1": "Burwing",
            "l_2": "Upper Burma",
            "l_3": "Magwe",
            "l_4": "Lashio",
            "l_5": "Loiwing",
            "l_6": "Akyab",
            "l_7": "Chittagong",
            "l_8": "Sittang Valley",
            "l_9": "Valley of the Irrawaddy",
            "l_10": "Andaman Islands"
        },
        "events": {
            "e_1": "enemy reconnaissance aircratt heard over the airfield",
            "e_2": "attacks on the aerodrome",
            "e_3": "Blenheims and P.40's destroyed",
            "e_4": "convoy left Magwe for Lashio and Loiwing",
            "e_5": "withdrawal of Burwing to Lashio and Loiwing",
            "e_6": "actions at Akyab",
            "e_7": "termination of the R.A.F. activities based in Burma"
        },
        "organisations": {
            "o_1": "R.A.F.",
            "o_2": "Air Headquarters, India",
            "o_3": "A.V.G."
        }
    },
    "keywords": [
        "enemy attacks",
        "reconnaissance",
        "Hurricanes",
        "Blenheims",
        "P.40's",
        "withdrawal",
        "Magwe",
        "Loiwing",
        "Akyab",
        "R.D.F.",
        "fighter escort"
    ],
    "themes": [
        "Military Operations",
        "Air Defense",
        "Strategic Withdrawals",
        "Aircraft Losses"
    ],
    "topicModel": {
        "Military Operations": [
            "e_1",
            "e_2",
            "e_6"
        ],
        "Strategic Withdrawals": [
            "e_4",
            "e_5"
        ],
        "Aircraft Losses": [
            "e_3",
            "e_7"
        ]
    },
    "eventConnections": [
        {
            "event": "e_1",
            "date": "March 22",
            "locations": [
                "l_3"
            ],
            "persons": [],
            "organisations": [
                "o_1",
                "o_3"
            ],
            "connectedEvents": [
                "e_2"
            ],
            "eventSummary": "The enemy conducts a reconnaissance mission over the airfield."
        },
        {
            "event": "e_2",
            "date": "March 22",
            "locations": [
                "l_3"
            ],
            "persons": [],
            "organisations": [
                "o_1"
            ],
            "connectedEvents": [
                "e_3"
            ],
            "eventSummary": "Significant enemy attacks occur against the aerodrome, resulting in considerable damage."
        },
        {
            "event": "e_3",
            "date": "",
            "locations": [
                "l_1"
            ],
            "persons": [],
            "organisations": [
                "o_1"
            ],
            "connectedEvents": [],
            "eventSummary": "A total of 9 Blenheims and at least 3 P.40's are destroyed on the ground due to enemy action."
        },
        {
            "event": "e_4",
            "date": "March 23",
            "locations": [
                "l_3",
                "l_4",
                "l_5"
            ],
            "persons": [],
            "organisations": [],
            "connectedEvents": [
                "e_5"
            ],
            "eventSummary": "A convoy departs from Magwe for Lashio and Loiwing."
        },
        {
            "event": "e_5",
            "date": "",
            "locations": [
                "l_1",
                "l_4",
                "l_5"
            ],
            "persons": [
                "p_2",
                "p_3"
            ],
            "organisations": [],
            "connectedEvents": [],
            "eventSummary": "Confirmation is received that Burwing will be withdrawn to Loiwing and Lashio."
        },
        {
            "event": "e_6",
            "date": "March 23 to 27",
            "locations": [
                "l_6"
            ],
            "persons": [],
            "organisations": [
                "o_1"
            ],
            "connectedEvents": [],
            "eventSummary": "Enemy actions occur at Akyab, with interception attempts by fighters."
        },
        {
            "event": "e_7",
            "date": "",
            "locations": [
                "l_1"
            ],
            "persons": [],
            "organisations": [
                "o_1"
            ],
            "connectedEvents": [],
            "eventSummary": "The R.A.F. activities based in Burma effectively come to an end as a result of these engagements."
        }
    ]
}