{
    "name": "Brigadier Lloyd",
    "mentions": [
        {
            "name": "Brigadier Lloyd",
            "url_handle": "brigadier-lloyd",
            "issue": "37638",
            "page": "19",
            "file_path": "/Users/tanyagray/Documents/code/POC/iiif-wwii-despatches/collection/world-war-2-despatches/index/37638/page_19.json",
            "timestamp": "2025-02-10T23:03:18.257028",
            "first_appearance": {
                "issue": "37638",
                "page": "19"
            },
            "frequency_count": 1,
            "related_events": [
                "Capture of Damascus"
            ],
            "related_locations": [
                "Syria"
            ],
            "related_organisations": [
                "7th Australian Division",
                "5th Indian Brigade"
            ],
            "event_dates": [
                "not specified"
            ],
            "rank_title": null,
            "aliases": []
        },
        {
            "name": "Brigadier Lloyd",
            "url_handle": "brigadier-lloyd",
            "issue": "37638",
            "page": "18",
            "file_path": "/Users/tanyagray/Documents/code/POC/iiif-wwii-despatches/collection/world-war-2-despatches/index/37638/page_18.json",
            "timestamp": "2025-02-10T23:03:18.259554",
            "first_appearance": {
                "issue": "37638",
                "page": "18"
            },
            "frequency_count": 1,
            "related_events": [
                "Capture of Damascus"
            ],
            "related_locations": [
                "Damascus"
            ],
            "related_organisations": [
                "Free French",
                "5th Indian Infantry Brigade"
            ],
            "event_dates": [
                "21st June"
            ],
            "rank_title": null,
            "aliases": []
        },
        {
            "name": "Brigadier Lloyd",
            "url_handle": "brigadier-lloyd",
            "issue": "37628",
            "page": "3",
            "file_path": "/Users/tanyagray/Documents/code/POC/iiif-wwii-despatches/collection/world-war-2-despatches/index/37628/page_3.json",
            "timestamp": "2025-02-10T23:03:18.323961",
            "first_appearance": {
                "issue": "37628",
                "page": "3"
            },
            "frequency_count": 1,
            "related_events": [
                "Battle of Sidi Barrani",
                "attack on Tummar"
            ],
            "related_locations": [
                "Sidi Barrani",
                "Tummar",
                "Nibeiwa"
            ],
            "related_organisations": [
                "4th Indian Division",
                "7th Armoured Division",
                "16th British Infantry Brigade",
                "5th Indian Infantry Brigade",
                "7th Battalion R.T.R.",
                "11th Indian Infantry Brigade"
            ],
            "event_dates": [
                "9th December",
                "9th December"
            ],
            "rank_title": null,
            "aliases": []
        }
    ],
    "first_appearance": {
        "issue": "37638",
        "page": "19"
    },
    "frequency_count": 3,
    "aliases": []
}