{
    "name": "Captain Maund",
    "mentions": [
        {
            "name": "Captain Maund",
            "url_handle": "captain-maund",
            "issue": "38171",
            "page": "7",
            "file_path": "/Users/tanyagray/Documents/code/POC/iiif-wwii-despatches/collection/world-war-2-despatches/index/38171/page_7.json",
            "timestamp": "2025-02-11T10:43:00.443450",
            "first_appearance": {
                "issue": "38171",
                "page": "7"
            },
            "frequency_count": 1,
            "related_events": [],
            "related_locations": [],
            "related_organisations": [],
            "event_dates": [],
            "rank_title": "Captain",
            "aliases": []
        },
        {
            "name": "Captain Maund",
            "url_handle": "captain-maund",
            "issue": "38011",
            "page": "15",
            "file_path": "/Users/tanyagray/Documents/code/POC/iiif-wwii-despatches/collection/world-war-2-despatches/index/38011/page_15.json",
            "timestamp": "2025-02-11T10:43:00.701547",
            "first_appearance": {
                "issue": "38011",
                "page": "15"
            },
            "frequency_count": 1,
            "related_events": [],
            "related_locations": [],
            "related_organisations": [],
            "event_dates": [],
            "rank_title": "Captain",
            "aliases": []
        }
    ],
    "first_appearance": {
        "issue": "38171",
        "page": "7"
    },
    "frequency_count": 2,
    "aliases": []
}