{
    "name": "Chief Gerasu Duke",
    "mentions": [
        {
            "name": "Chief Gerasu Duke",
            "url_handle": "chief-gerasu-duke",
            "issue": "37645",
            "page": "67",
            "file_path": "../../collection/world-war-2-despatches/index/37645/page_67.json",
            "timestamp": "2025-02-05T12:26:45.925108",
            "first_appearance": {
                "issue": "37645",
                "page": "67"
            },
            "frequency_count": 1,
            "related_events": [
                "Occupation of Bedelle"
            ],
            "related_locations": [
                "Bedelle"
            ],
            "related_organisations": [
                "British troops"
            ],
            "event_dates": [
                "June 20, 1946"
            ],
            "rank_title": null,
            "aliases": []
        }
    ],
    "first_appearance": {
        "issue": "37645",
        "page": "67"
    },
    "frequency_count": 1,
    "aliases": []
}