{
    "namedEntities": {
        "persons": {
            "p_1": "Group Captain E. B. Rice"
        },
        "locations": {
            "l_1": "Central Malaya",
            "l_2": "Kuala Lumpur",
            "l_3": "Singapore",
            "l_4": "Rhio Archipelago",
            "l_5": "Mersing",
            "l_6": "Tanah Merah Besar",
            "l_7": "Bukit Chunang",
            "l_8": "Tanjong Kupang",
            "l_9": "Kota Tingi",
            "l_10": "Kota Bahru",
            "l_11": "Alor Star",
            "l_12": "Tengah",
            "l_13": "Sembawang",
            "l_14": "Seletar"
        },
        "events": {
            "e_1": "Formation of Air Defence System",
            "e_2": "Facilities Development for Radar"
        },
        "organisations": {
            "o_1": "Observer Corps",
            "o_2": "A.H.Q.",
            "o_3": "R.A.A.F."
        }
    },
    "keywords": [
        "Blenheim",
        "H.Q.",
        "Radar",
        "Fighter Operations",
        "Training",
        "Observer Posts",
        "Squadrons",
        "Air Defence"
    ],
    "themes": [
        "Military Operations",
        "Training and Development",
        "Air Defence"
    ],
    "topicModel": {
        "Military Operations": [
            "e_1",
            "e_2"
        ],
        "Training and Development": [
            "e_1"
        ],
        "Air Defence": [
            "e_1",
            "e_2"
        ]
    },
    "eventConnections": [
        {
            "event": "e_1",
            "date": "October 1941",
            "locations": [
                "Central Malaya",
                "Kuala Lumpur",
                "Singapore"
            ],
            "persons": [
                "p_1"
            ],
            "organisations": [
                "o_1",
                "o_2"
            ],
            "connectedEvents": [
                "e_2"
            ],
            "eventSummary": "An Air Defence system is in place by the time war comes, providing a significant defensive effort despite limitations."
        },
        {
            "event": "e_2",
            "date": "July 1941",
            "locations": [
                "Kuala Lumpur",
                "Singapore"
            ],
            "persons": [],
            "organisations": [
                "o_1",
                "o_2"
            ],
            "connectedEvents": [],
            "eventSummary": "Development of radar facilities is prioritized for locations such as Singapore Island and the East Coast of Malaya."
        }
    ]
}