{
    "@context": "https://schema.org",
    "@type": "Person",
    "name": "Major Young",
    "givenName": "Major",
    "familyName": "Young",
    "honorificPrefix": "Major",
    "honorificSuffix": null,
    "identifier": "major-young",
    "url": "https://unlockingthepast.com/id/major-young",
    "alternateName": [],
    "subjectOf": {
        "@type": "CreativeWork",
        "name": "World War II Despatches",
        "identifier": "38190",
        "pagination": "19",
        "url": "https://unlockingthepast.com/collection/world-war-2-despatches/discover/38190/#19",
        "mentions": [
            {
                "@type": "Person",
                "name": "Major Young",
                "givenName": "Major",
                "familyName": "Young",
                "honorificPrefix": "Major",
                "honorificSuffix": null,
                "identifier": "major-young",
                "url": "https://unlockingthepast.com/id/major-young"
            },
            {
                "@type": "Event",
                "name": "Reports of enemy strength at Repulse Bay",
                "identifier": "reports-of-enemy-strength-at-repulse-bay",
                "url": "https://unlockingthepast.com/id/reports-of-enemy-strength-at-repulse-bay"
            },
            {
                "@type": "Place",
                "name": "Repulse Bay Hotel",
                "identifier": "repulse-bay-hotel",
                "url": "https://unlockingthepast.com/id/repulse-bay-hotel"
            },
            {
                "@type": "Organization",
                "name": "East Infantry Brigade",
                "identifier": "east-infantry-brigade",
                "url": "https://unlockingthepast.com/id/east-infantry-brigade"
            }
        ],
        "datePublished": "1940-12-20"
    }
}