{
    "@context": "https://schema.org",
    "@type": "Person",
    "name": "Sir Trafford Leigh-Mallory",
    "givenName": "Trafford",
    "familyName": "Leigh-Mallory",
    "honorificPrefix": "Sir",
    "honorificSuffix": null,
    "identifier": "sir-trafford-leigh-mallory",
    "url": "https://unlockingthepast.com/id/sir-trafford-leigh-mallory",
    "alternateName": [],
    "subjectOf": [
        {
            "@type": "CreativeWork",
            "name": "World War II Despatches",
            "identifier": "37838",
            "pagination": "1",
            "url": "https://unlockingthepast.com/collection/world-war-2-despatches/discover/37838/#1",
            "mentions": [
                {
                    "@type": "Person",
                    "name": "Sir Trafford Leigh-Mallory",
                    "givenName": "Trafford",
                    "familyName": "Leigh-Mallory",
                    "honorificPrefix": "Sir",
                    "honorificSuffix": null,
                    "identifier": "sir-trafford-leigh-mallory",
                    "url": "https://unlockingthepast.com/id/sir-trafford-leigh-mallory"
                },
                {
                    "@type": "Event",
                    "name": "Air Operations by the Allied Expeditionary Air Force",
                    "identifier": "air-operations-by-the-allied-expeditionary-air-force",
                    "url": "https://unlockingthepast.com/id/air-operations-by-the-allied-expeditionary-air-force"
                },
                {
                    "@type": "Event",
                    "name": "Disbandment of A.E.A.F.",
                    "identifier": "disbandment-of-a-e-a-f",
                    "url": "https://unlockingthepast.com/id/disbandment-of-a-e-a-f"
                },
                {
                    "@type": "Place",
                    "name": "N.W. Europe",
                    "identifier": "n-w-europe",
                    "url": "https://unlockingthepast.com/id/n-w-europe"
                },
                {
                    "@type": "Place",
                    "name": "Great Britain",
                    "identifier": "great-britain",
                    "url": "https://unlockingthepast.com/id/great-britain"
                },
                {
                    "@type": "Place",
                    "name": "United Kingdom",
                    "identifier": "united-kingdom",
                    "url": "https://unlockingthepast.com/id/united-kingdom"
                },
                {
                    "@type": "Organization",
                    "name": "United States Eighth Air Force",
                    "identifier": "united-states-eighth-air-force",
                    "url": "https://unlockingthepast.com/id/united-states-eighth-air-force"
                },
                {
                    "@type": "Organization",
                    "name": "Royal Air Force Coastal Command",
                    "identifier": "royal-air-force-coastal-command",
                    "url": "https://unlockingthepast.com/id/royal-air-force-coastal-command"
                },
                {
                    "@type": "Organization",
                    "name": "Allied Expeditionary Air Force",
                    "identifier": "allied-expeditionary-air-force",
                    "url": "https://unlockingthepast.com/id/allied-expeditionary-air-force"
                },
                {
                    "@type": "Organization",
                    "name": "Royal Air Force Bomber Command",
                    "identifier": "royal-air-force-bomber-command",
                    "url": "https://unlockingthepast.com/id/royal-air-force-bomber-command"
                },
                {
                    "@type": "Organization",
                    "name": "Combined Chiefs of Staff",
                    "identifier": "combined-chiefs-of-staff",
                    "url": "https://unlockingthepast.com/id/combined-chiefs-of-staff"
                }
            ],
            "datePublished": "1943-11-15"
        },
        {
            "@type": "CreativeWork",
            "name": "World War II Despatches",
            "identifier": "38437",
            "pagination": "1",
            "url": "https://unlockingthepast.com/collection/world-war-2-despatches/discover/38437/#1",
            "mentions": [
                {
                    "@type": "Person",
                    "name": "Sir Trafford Leigh-Mallory",
                    "givenName": "Trafford",
                    "familyName": "Leigh-Mallory",
                    "honorificPrefix": "Sir",
                    "honorificSuffix": null,
                    "identifier": "sir-trafford-leigh-mallory",
                    "url": "https://unlockingthepast.com/id/sir-trafford-leigh-mallory"
                },
                {
                    "@type": "Event",
                    "name": "Allied Expeditionary Air Force",
                    "identifier": "allied-expeditionary-air-force2",
                    "url": "https://unlockingthepast.com/id/allied-expeditionary-air-force2"
                },
                {
                    "@type": "Place",
                    "name": "Europe",
                    "identifier": "europe",
                    "url": "https://unlockingthepast.com/id/europe"
                },
                {
                    "@type": "Organization",
                    "name": "Fighter Command",
                    "identifier": "fighter-command",
                    "url": "https://unlockingthepast.com/id/fighter-command"
                }
            ],
            "datePublished": "1944-10-14"
        }
    ]
}