{
    "namedEntities": {
        "persons": {
            "p_1": "H. M. L. Waller",
            "p_2": "C. W. May",
            "p_3": "T. J. Cain",
            "p_4": "Gretton"
        },
        "locations": {
            "l_1": "Tanjong Priok",
            "l_2": "Bawean Island",
            "l_3": "Sourabaya"
        },
        "events": {
            "e_1": "Action of 27th February 1942",
            "e_2": "Counter-attack by ELECTRA"
        },
        "organisations": {
            "o_1": "Royal Australian Navy",
            "o_2": "Royal Navy"
        }
    },
    "keywords": [
        "submarine",
        "destroyers",
        "Allied force",
        "electra",
        "enemy",
        "casualties"
    ],
    "themes": [
        "Military Operations",
        "Naval Engagement",
        "Combat Readiness"
    ],
    "topicModel": {
        "Military Operations": [
            "e_1",
            "e_2"
        ],
        "Naval Engagement": [
            "e_1",
            "e_2"
        ]
    },
    "eventConnections": [
        {
            "event": "e_1",
            "date": "27th February 1942",
            "locations": [
                "l_1",
                "l_2",
                "l_3"
            ],
            "persons": [
                "p_1",
                "p_2",
                "p_3"
            ],
            "organisations": [
                "o_1",
                "o_2"
            ],
            "connectedEvents": [
                "e_2"
            ],
            "eventSummary": "The Allied force engages the enemy at sea, with the ELECTRA involved in significant combat. The action sees heavy exchanges but does not achieve clear victory."
        },
        {
            "event": "e_2",
            "date": null,
            "locations": [],
            "persons": [
                "p_2",
                "p_3",
                "p_4"
            ],
            "organisations": [],
            "connectedEvents": [
                "e_1"
            ],
            "eventSummary": "Following initial engagements, ELECTRA is ordered to counter-attack but suffers significant damage, leading to eventual abandonment of the ship."
        }
    ]
}