{
    "namedEntities": {
        "persons": {
            "p_1": "A.O.C. Malta"
        },
        "locations": {
            "l_1": "Malta",
            "l_2": "Sicily",
            "l_3": "Southern Italy",
            "l_4": "Tripoli",
            "l_5": "Benghazi",
            "l_6": "Alexandria",
            "l_7": "Suda Bay",
            "l_8": "Ionian Sea",
            "l_9": "Eastern Mediterranean",
            "l_10": "Kerkenna Islands"
        },
        "events": {
            "e_1": "Attack on Catania aerodrome",
            "e_2": "Counter-offensive in Cyrenaica",
            "e_3": "Air attacks on Malta",
            "e_4": "Bombing attacks on enemy shipping"
        },
        "organisations": {
            "o_1": "No. 26x (F) Squadron",
            "o_2": "No. 228 (F/B) Squadron",
            "o_3": "No. 431 G.R. Flight",
            "o_4": "No. 148 (B) Squadron",
            "o_5": "Fleet Air Arm",
            "o_6": "No. 21 (B) Squadron"
        }
    },
    "keywords": [
        "German Air Force",
        "Hurricanes",
        "Wellingtons",
        "Spitfire",
        "Sunderlands",
        "bombing",
        "reconnaissance"
    ],
    "themes": [
        "Military Operations",
        "Air Defense",
        "Reconnaissance",
        "Counter-Offensives"
    ],
    "topicModel": {
        "Military Operations": [
            "e_1",
            "e_2",
            "e_4"
        ],
        "Air Defense": [
            "e_3"
        ],
        "Reconnaissance": [
            "e_1"
        ],
        "Counter-Offensives": [
            "e_2"
        ]
    },
    "eventConnections": [
        {
            "event": "e_1",
            "date": "15/16 January",
            "locations": [
                "l_1"
            ],
            "persons": [
                "p_1"
            ],
            "organisations": [
                "o_4"
            ],
            "connectedEvents": [
                "e_3"
            ],
            "eventSummary": "An especially successful attack is made on Catania aerodrome, where 35 German aircraft are reported destroyed on the ground by 9 Wellingtons."
        },
        {
            "event": "e_2",
            "date": "April",
            "locations": [
                "l_1",
                "l_4"
            ],
            "persons": [
                "p_1"
            ],
            "organisations": [
                "o_6"
            ],
            "connectedEvents": [
                "e_1"
            ],
            "eventSummary": "A counter-offensive in Cyrenaica leads to the resumption of operations against Tripoli from Malta."
        },
        {
            "event": "e_3",
            "date": "January",
            "locations": [
                "l_1"
            ],
            "persons": [
                "p_1"
            ],
            "organisations": [
                "o_1",
                "o_2",
                "o_3",
                "o_4"
            ],
            "connectedEvents": [
                "e_4"
            ],
            "eventSummary": "Throughout January, the enemy makes persistent and heavy-scale air attacks on Malta, targeting the Grand Harbour and naval facilities."
        },
        {
            "event": "e_4",
            "date": "1st May",
            "locations": [
                "l_1",
                "l_10"
            ],
            "persons": [],
            "organisations": [
                "o_6"
            ],
            "connectedEvents": [],
            "eventSummary": "On 1st May, 6 Blenheims of No. 21 Squadron bomb enemy shipping near Kerkenna Islands, achieving several direct hits."
        }
    ]
}