{
    "namedEntities": {
        "persons": {
            "p_1": "Admiral Sir Andrew Cunningham",
            "p_2": "General Sir Archibald Wavell",
            "p_3": "Sir Miles Lampson",
            "p_4": "ARTHUR M. LONGMORE"
        },
        "locations": {
            "l_1": "Cyrenaica",
            "l_2": "Greece",
            "l_3": "Libya",
            "l_4": "Eritrea",
            "l_5": "Italian Somaliland",
            "l_6": "Middle East",
            "l_7": "U.K.",
            "l_8": "Egypt"
        },
        "events": {
            "e_1": "Withdrawal from Cyrenaica",
            "e_2": "Campaigns in Greece",
            "e_3": "Co-operation with Egyptian Government"
        },
        "organisations": {
            "o_1": "Royal Air Force",
            "o_2": "Egyptian Government"
        }
    },
    "keywords": [
        "withdrawal",
        "co-operation",
        "Air commitments",
        "long lines of communication"
    ],
    "themes": [
        "Military Operations",
        "Diplomacy",
        "Strategic Decisions"
    ],
    "topicModel": {
        "Military Operations": [
            "e_1",
            "e_2"
        ],
        "Diplomacy": [
            "e_3"
        ],
        "Strategic Decisions": [
            "e_1"
        ]
    },
    "eventConnections": [
        {
            "event": "e_1",
            "date": "April 1941",
            "locations": [
                "l_1"
            ],
            "persons": [
                "p_1",
                "p_2"
            ],
            "organisations": [
                "o_1"
            ],
            "connectedEvents": [
                "e_2"
            ],
            "eventSummary": "The withdrawal from Cyrenaica occurs in April 1941, reflecting challenges during military operations."
        },
        {
            "event": "e_2",
            "date": "",
            "locations": [
                "l_2",
                "l_3",
                "l_4",
                "l_5"
            ],
            "persons": [
                "p_1",
                "p_2"
            ],
            "organisations": [
                "o_1"
            ],
            "connectedEvents": [
                "e_1"
            ],
            "eventSummary": "The campaigns in Greece are discussed, highlighting military difficulties faced by the forces."
        },
        {
            "event": "e_3",
            "date": "",
            "locations": [
                "l_8"
            ],
            "persons": [
                "p_3",
                "p_4"
            ],
            "organisations": [
                "o_2"
            ],
            "connectedEvents": [],
            "eventSummary": "The report concludes with thanks to Sir Miles Lampson for his support in dealings with the Egyptian Government."
        }
    ]
}