{
    "namedEntities": {
        "persons": {
            "p_1": "Commandant Paris",
            "p_2": "General Bethouart",
            "p_3": "Brigadier Gubbins",
            "p_4": "Commander Hubback",
            "p_5": "Colonel Dowler",
            "p_6": "Lord Cork"
        },
        "locations": {
            "l_1": "Narvik",
            "l_2": "Bodo",
            "l_3": "Beisfjord",
            "l_4": "Ankenes Peninsula",
            "l_5": "Fagernes",
            "l_6": "Forsneset",
            "l_7": "Sildvik",
            "l_8": "Hundalen",
            "l_9": "Bardu Foss"
        },
        "events": {
            "e_1": "Landing Operation",
            "e_2": "Evacuation of Bodo"
        },
        "organisations": {
            "o_1": "French Forces",
            "o_2": "Royal Navy",
            "o_3": "His Majesty's Government"
        }
    },
    "keywords": [
        "landing operation",
        "evacuation",
        "French troops",
        "air attacks",
        "Bodo",
        "Narvik"
    ],
    "themes": [
        "Military Operations",
        "Evacuation",
        "Leadership",
        "Air Support"
    ],
    "topicModel": {
        "Military Operations": [
            "e_1",
            "e_2"
        ],
        "Evacuation": [
            "e_2"
        ],
        "Leadership": [
            "e_1"
        ],
        "Air Support": [
            "e_1"
        ]
    },
    "eventConnections": [
        {
            "event": "e_1",
            "date": "27th May – 29th May",
            "locations": [
                "l_1",
                "l_3"
            ],
            "persons": [
                "p_1",
                "p_2",
                "p_4"
            ],
            "organisations": [
                "o_1",
                "o_2"
            ],
            "connectedEvents": [
                "e_2"
            ],
            "eventSummary": "The landing operation is initiated where forward troops fight to maintain positions while facing enemy attacks. General Bethouart's forces eventually secure the area after overcoming initial resistance."
        },
        {
            "event": "e_2",
            "date": "Post Instructions from His Majesty's Government",
            "locations": [
                "l_2"
            ],
            "persons": [
                "p_3",
                "p_5",
                "p_6"
            ],
            "organisations": [
                "o_3",
                "o_1"
            ],
            "connectedEvents": [],
            "eventSummary": "The evacuation of Bodo is planned and executed promptly to save personnel amidst heavy air attacks. Colonel Dowler is dispatched to coordinate the withdrawal of troops."
        }
    ]
}